setup.py
faraffle/__init__.py
faraffle/__main__.py
faraffle.egg-info/PKG-INFO
faraffle.egg-info/SOURCES.txt
faraffle.egg-info/dependency_links.txt
faraffle.egg-info/entry_points.txt
faraffle.egg-info/requires.txt
faraffle.egg-info/top_level.txt