Metadata-Version: 1.1
Name: faraffle
Version: 0.0.2
Summary: Easy script for selecting FA raffle winners
Home-page: https://github.com/Dreae
Author: Dreae
Author-email: penitenttangentt@gmail.com
License: MIT License
Platform: UNKNOWN
Classifier: Development Status :: 4 - Beta
